{
  "video_duration": "0:00:39.973307",
  "objects_count": {
    "cow": 53,
    "bear": 29,
    "dog": 30,
    "zebra": 175,
    "bird": 4,
    "person": 39,
    "horse": 72,
    "elephant": 74,
    "giraffe": 17,
    "sheep": 3,
    "bench": 3,
    "teddy bear": 1,
    "traffic light": 1,
    "bottle": 1,
    "All": 502
  },
  "objects_loc": {
    "cow": {
      "time": [
        [
          19.19,
          19.22
        ],
        [
          29.83,
          32.77
        ],
        [
          34.43,
          34.47
        ],
        [
          36.1,
          36.9
        ]
      ],
      "frames": [
        "https://i.imgur.com/dG5rl3u.jpeg"
      ]
    },
    "bear": {
      "time": [
        [
          0,
          3.94
        ]
      ],
      "frames": [
        "https://i.imgur.com/dG5rl3u.jpeg"
      ]
    },
    "dog": {
      "time": [
        [
          1.17,
          4.6
        ]
      ],
      "frames": [
        "https://i.imgur.com/dG5rl3u.jpeg"
      ]
    },
    "zebra": {
      "time": [
        [
          4.6,
          7.81
        ],
        [
          10.48,
          15.22
        ],
        [
          29.66,
          29.7
        ]
      ],
      "frames": [
        "https://i.imgur.com/dG5rl3u.jpeg"
      ]
    },
    "bird": {
      "time": [
        [
          1.72,
          4.76
        ]
      ],
      "frames": [
        "https://i.imgur.com/dG5rl3u.jpeg",
        "https://i.imgur.com/dG5rl3u.jpeg",
        "https://i.imgur.com/dG5rl3u.jpeg"

      ]
    },
    "person": {
      "time": [
        [
          4.57,
          4.64
        ],
        [
          7.67,
          7.77
        ],
        [
          15.12,
          19.29
        ],
        [
          26.16,
          26.23
        ],
        [
          28.06,
          29.56
        ] 
      ],
      "frames": [
        "/home/hp/Machine Learning/videoObjectDetection/app/processed/frame61.jpg"
      ]
    },
    "horse": {
      "time": [
       
        [
          2.44,
          4.47
        ]
      ],
      "frames": [
        "/home/hp/Machine Learning/videoObjectDetection/app/processed/frame42.jpg"
      ]
    },
    "elephant": {
      "time": [
        [
          11.75,
          12.78
        ],
        [
          12.68,
          13.71
        ]
      ],
      "frames": [
        "/home/hp/Machine Learning/videoObjectDetection/app/processed/frame380.jpg"
      ]
    },
    "giraffe": {
      "time": [
        [
          37.87,
          39.9
        ]
       
      ],
      "frames": [
        "/home/hp/Machine Learning/videoObjectDetection/app/processed/frame1145.jpg"
      ]
    },
    "sheep": {
      "time": [
        [
          29.66,
          33.7
        ],
        [
          7.67,
          11.71
        ]
      ],
      "frames": [
        "/home/hp/Machine Learning/videoObjectDetection/app/processed/frame230.jpg"
      ]
    },
    "bench": {
      "time": [
        [
          17.98,
          18.02
        ],
        [
          1.2,
          3.23
        ]
      ],
      "frames": [
        "/home/hp/Machine Learning/videoObjectDetection/app/processed/frame36.jpg"
      ]
    },
    "teddy bear": {
      "time": [
        [
          7.67,
          14.71
        ]
      ],
      "frames": [
        "/home/hp/Machine Learning/videoObjectDetection/app/processed/frame230.jpg"
      ]
    },
    "traffic light": {
      "time": [
        [
          2.8,
          5.84
        ]
      ],
      "frames": [
        "/home/hp/Machine Learning/videoObjectDetection/app/processed/frame84.jpg"
      ]
    },
    "bottle": {
      "time": [
        [
          0.00,
          1.47
        ]
      ],
      "frames": [
        "/home/hp/Machine Learning/videoObjectDetection/app/processed/frame13.jpg"
      ]
    }
  }
}